Workbook

Sheet DRE
B2: REGIME TRIBUTÁRIO | C2: LUCRO REAL
B3: ANEXO SIMPLES | C3: ANEXO I - COMÉRCIO
B4: RB 12 | C4: 500000
B5: FAIXA DO SIMPLES | C5: =IF(C2="SIMPLES NACIONAL",IF(C4<=180000,"1ª FAIXA",IF(C4<=360000,"2ª FAIXA",IF(C4<=720000,"3ª FAIXA",IF(C4<=1800000,"4ª FAIXA",IF(C4<=3600000,"5ª FAIXA",IF(C4<=4800000,"6ª FAIXA","FORA DO SIMPLES")))))),"-") -> -
B6: ALÍQUOTA EFETIVA SIMPLES | C6: =IF(C2="SIMPLES NACIONAL",VLOOKUP(C4,'ANEXOS SN DRE'!F2:G39,2,FALSE),0) -> 0
B7: ALÍQUOTA 2027 SN HÍBRIDO | C7: =IF(C2="SIMPLES NACIONAL",(C6-(VLOOKUP(C4,'ANEXOS SN DRE'!F2:V39,17,FALSE))),0) -> 0
B8: TIPO PRODUTO/SERVIÇO | C8: Bens Imóveis (Venda e Incorporação)
B9: % DE REDUÇÃO IBS E CBS | C9: =VLOOKUP(C8,CORES!A7:B31,2,FALSE) -> 0.5
B10: CBS | C10: =0.093*(1-C9) -> 0.0465
B12: VALOR DA RECEITA BRUTA | C12: 250000
B13: ALÍQUOTA ICMS SAÍDA | C13: 0
B14: ALÍQUOTA ISS SAÍDA | C14: 0.05
B15: ALÍQUOTA PIS/COFINS | C15: =IF(C2="LUCRO REAL",9.25%,IF(C2="LUCRO PRESUMIDO",3.65%,0)) -> 0.0925
B16: CUSTOS | C16: 104500
B17: DESPESAS - PJ | C17: 30000
B18: DESPESAS - PF/NÃO CONTRIBUINTES | C18: 1000
B19: FOLHA DE PAGAMENTO | C19: 55000
B22: ANO | C22: 2026 | D22: 2027 - LUCRO REAL | E22: 2027 - LUCRO PRESUMIDO | F22: 2027 - SN HÍBRIDO | G22: 2027 - SN REGULAR
B23: RECEITA BRUTA | C23: =C12 -> 250000 | D23: =C23-(C23*9.25%) -> 226875 | E23: =C23-(C23*3.65%) -> 240875 | F23: =C12-(C12*(C6-C7)) -> 250000 | G23: =C12 -> 250000
B24: SIMPLES NACIONAL | C24: =IF(C2="SIMPLES NACIONAL",C23*C6,0) -> 0 | D24: NÃO INCIDENTE | E24: NÃO INCIDENTE | F24: =F23*C7 -> 0 | G24: =G23*C6 -> 0
B25: ICMS/ISS | C25: =IF(C2="SIMPLES NACIONAL",0,(C23*(C14+C13))) -> 12500 | D25: =(D23+D27)*(C13+C14) -> 11871.234 | E25: =(E23+E27)*(C13+C14) -> 12603.784 | F25: NÃO INCIDENTE | G25: NÃO INCIDENTE
B26: PIS/COFINS | C26: =C23*C15 -> 23125 | D26: EXTINTO | E26: EXTINTO | F26: EXTINTO | G26: EXTINTO
B27: CBS | C27: NÃO INCIDENTE | D27: =D23*C10 -> 10549.688 | E27: =E23*C10 -> 11200.688 | F27: =F23*C10 -> 11625 | G27: NÃO INCIDENTE
B28: RECEITA LÍQUIDA | C28: =C23-C24-C25-C26 -> 214375 | D28: =D23-D25 -> 215003.77 | E28: =E23-E25 -> 228271.22 | F28: =F23-F24 -> 250000 | G28: =G23-G24 -> 250000
B29: CUSTOS | C29: =C16 -> 104500 | D29: =C16 -> 104500 | E29: =C16 -> 104500 | F29: =E29 -> 104500 | G29: =F29 -> 104500
B30: CRÉDITO TRIBUTÁRIO S/ CUSTOS | C30: =IF(C2="LUCRO REAL",-C16*0.0925,0) -> -9666.25 | D30: =-D29*9.3% -> -9718.5 | E30: =-E29*9.3% -> -9718.5 | F30: =-F29*9.3% -> -9718.5 | G30: 0
B31: LUCRO BRUTO | C31: =C28-C29-C30 -> 119541.25 | D31: =D28-D29-D30 -> 120222.27 | E31: =E28-E29-E30 -> 133489.72 | F31: =F28-F29-F30 -> 155218.5 | G31: =G28-G29-G30 -> 145500
B32: DESPESAS - PJ | C32: =C17 -> 30000 | D32: =C32 -> 30000 | E32: =D32 -> 30000 | F32: =E32 -> 30000 | G32: =F32 -> 30000
B33: CRÉDITO TRIBUTÁRIO S/ DESPESAS | C33: 0 | D33: =-D32*9.3% -> -2790 | E33: =-E32*9.3% -> -2790 | F33: =E33 -> -2790 | G33: 0
B34: DESPESAS - PJ/NÃO CONTRIBUINTES | C34: =C18 -> 1000 | D34: =C34 -> 1000 | E34: =D34 -> 1000 | F34: =E34 -> 1000 | G34: =F34 -> 1000
B35: FOLHA DE PAGAMENTO | C35: =C19 -> 55000 | D35: =C35 -> 55000 | E35: =D35 -> 55000 | F35: =E35 -> 55000 | G35: =F35 -> 55000
B36: IMPOSTOS S/ FOLHA | C36: =IF(C2="SIMPLES NACIONAL",0,C35*0.26) -> 14300 | D36: =D35*0.26 -> 14300 | E36: =E35*0.26 -> 14300 | F36: NÃO INCIDENTE | G36: NÃO INCIDENTE
B37: LUCRO/PREJUÍZO ANTES DO IR/CS | C37: =C31-C32-C33-C34-C35-C36 -> 19241.25 | D37: =D31-D32-D33-D34-D35-D36 -> 22712.266 | E37: =E31-E32-E33-E34-E35-E36 -> 35979.716 | F37: =F31-F32-F33-F34-F35 -> 72008.5 | G37: =G31-G32-G33-G34-G35 -> 59500
B38: PRESUNÇÃO IRPJ | C38: 0.32 | D38: - | E38: =C38 -> 0.32 | F38: - | G38: -
B39: PRESUNÇÃO CSLL | C39: 0.32 | D39: - | E39: =C39 -> 0.32 | F39: - | G39: -
B40: IRPJ + CSLL | C40: =IF(C2="LUCRO PRESUMIDO",((C23*C38)*0.25)+((C23*C39)*0.09),IF(C2="LUCRO REAL",IF(C37>0,C37*0.34,0),0)) -> 6542.025 | D40: =IF(D37>0,D37*34%,0) -> 7722.1703 | E40: =((E23*E38)*0.25)+((E23*E39)*0.09) -> 26207.2 | F40: 0 | G40: 0
B41: LUCRO/PREJUÍZO LÍQUIDO | C41: =C37-C40 -> 12699.225 | D41: =D37-D40 -> 14990.095 | E41: =E37-E40 -> 9772.5156 | F41: =F37-F40 -> 72008.5 | G41: =G37-G40 -> 59500

Sheet CORES
A4: #0041a5 | B4: #a0a0a0 | C4: #00affa | D4: #002d73 | E4: #0066cc | F4: #cdebff | G4: #4f4f4f | H4: #e6e6e6 | I4: #00c7a5 | J4: #ffd43b | K4: #ff6b6b
A7: Cesta Básica Nacional de Alimentos | B7: 1 | C7: 0
A8: Medicamentos (Doenças raras, oncologia, etc.) | B8: 1 | C8: 0
A9: Produtos hortícolas, frutas e ovos | B9: 1 | C9: 0
A10: Prouni (Educação Superior) | B10: 1 | C10: 0
A11: Automóveis (PcD, Autistas e Táxis) | B11: 1 | C11: 0
A12: Entidades de Ciência e Tecnologia (ICT) | B12: 1 | C12: 0
A13: Ato Cooperativo (Sist. Cooperativista) | B13: 1 | C13: 0
A14: Reabilitação Urbana (Áreas Críticas) | B14: 0.8 | C14: 0.0186
A15: Locação e Arrendamento de Imóveis | B15: 0.7 | C15: 0.0279
A16: Educação (Ensino Formal) | B16: 0.6 | C16: 0.0372
A17: Saúde (Serviços Gerais) | B17: 0.6 | C17: 0.0372
A18: Dispositivos Médicos e Acessibilidade | B18: 0.6 | C18: 0.0372
... A31: Outro - não listado | B31: 0 | C31: 0.093

Sheet ANEXOS SN DRE
A1: ANEXO I | B1: MÍNIMO | C1: MÁXIMO | D1: FAIXA | E1: DEDUZIR | I1: IRPJ | J1: CSLL | K1: CPP | L1: COFINS | M1: PIS | N1: ICMS | O1: ISS | P1: IPI | Q1: TOTAL | S1: IBS | U1: CBS | W1: RENDA
A2: 1ª FAIXA | B2: 0 | C2: 180000 | D2: 0.04 | E2: 0 | F2: =IF(DRE!$C$3="ANEXO I - COMÉRCIO",IF(DRE!$C$5="1ª FAIXA",DRE!$C$4,0),0) -> 0 | G2: =(F2*D2-E2)/F2 -> #DIV/0! | I2: 0.055 | J2: 0.035 | K2: 0.415 | L2: 0.1274 | M2: 0.0276 | N2: 0.34 | O2: 0 | P2: 0 | Q2: =SUM(I2:P2) -> 1 | S2: =N2+O2 -> 0.34 | T2: =S2*G2 -> #DIV/0! | U2: =L2+M2 -> 0.155 | V2: =U2*G2 -> #DIV/0! | W2: =Q2-S2-U2 -> 0.505 | X2: =W2*G2 -> #DIV/0!
A3: 2ª FAIXA | B3: =C2+0.01 -> 180000.01 | C3: =C2*2 -> 360000 | D3: 0.073 | E3: 5940 | F3: =IF(DRE!$C$3="ANEXO I - COMÉRCIO",IF(DRE!$C$5="2ª FAIXA",DRE!$C$4,0),0) -> 0 | G3: =(F3*D3-E3)/F3 -> #DIV/0! | I3: 0.055 | J3: 0.035 | K3: 0.415 | L3: 0.1274 | M3: 0.0276 | N3: 0.34 | O3: 0 | P3: 0 | Q3: =SUM(I3:P3) -> 1 | S3: =N3+O3 -> 0.34 | T3: =S3*G3 -> #DIV/0! | U3: =L3+M3 -> 0.155 | V3: =U3*G3 -> #DIV/0! | W3: =Q3-S3-U3 -> 0.505 | X3: =W3*G3 -> #DIV/0!
A4: 3ª FAIXA | B4: =C3+0.01 -> 360000.01 | C4: =C3*2 -> 720000 | D4: 0.095 | E4: 13860 | F4: =IF(DRE!$C$3="ANEXO I - COMÉRCIO",IF(DRE!$C$5="3ª FAIXA",DRE!$C$4,0),0) -> 0 | G4: =(F4*D4-E4)/F4 -> #DIV/0! | I4: 0.055 | J4: 0.035 | K4: 0.42 | L4: 0.1274 | M4: 0.0276 | N4: 0.335 | O4: 0 | P4: 0 | Q4: =SUM(I4:P4) -> 1 | S4: =N4+O4 -> 0.335 | T4: =S4*G4 -> #DIV/0! | U4: =L4+M4 -> 0.155 | V4: =U4*G4 -> #DIV/0! | W4: =Q4-S4-U4 -> 0.51 | X4: =W4*G4 -> #DIV/0!
A5: 4ª FAIXA | B5: =C4+0.01 -> 720000.01 | C5: 1800000 | D5: 0.107 | E5: 22500 | F5: =IF(DRE!$C$3="ANEXO I - COMÉRCIO",IF(DRE!$C$5="4ª FAIXA",DRE!$C$4,0),0) -> 0 | G5: =(F5*D5-E5)/F5 -> #DIV/0! | I5: 0.055 | J5: 0.035 | K5: 0.42 | L5: 0.1274 | M5: 0.0276 | N5: 0.335 | O5: 0 | P5: 0 | Q5: =SUM(I5:P5) -> 1 | S5: =N5+O5 -> 0.335 | T5: =S5*G5 -> #DIV/0! | U5: =L5+M5 -> 0.155 | V5: =U5*G5 -> #DIV/0! | W5: =Q5-S5-U5 -> 0.51 | X5: =W5*G5 -> #DIV/0!
A6: 5ª FAIXA | B6: =C5+0.01 -> 1800000 | C6: =C5*2 -> 3600000 | D6: 0.143 | E6: 87300 | F6: =IF(DRE!$C$3="ANEXO I - COMÉRCIO",IF(DRE!$C$5="5ª FAIXA",DRE!$C$4,0),0) -> 0 | G6: =(F6*D6-E6)/F6 -> #DIV/0! | I6: 0.055 | J6: 0.035 | K6: 0.42 | L6: 0.1274 | M6: 0.0276 | N6: 0.335 | O6: 0 | P6: 0 | Q6: =SUM(I6:P6) -> 1 | S6: =N6+O6 -> 0.335 | T6: =S6*G6 -> #DIV/0! | U6: =L6+M6 -> 0.155 | V6: =U6*G6 -> #DIV/0! | W6: =Q6-S6-U6 -> 0.51 | X6: =W6*G6 -> #DIV/0!
A7: 6ª FAIXA | B7: =C6+0.01 -> 3600000 | C7: 4800000 | D7: 0.19 | E7: 378000 | F7: =IF(DRE!$C$3="ANEXO I - COMÉRCIO",IF(DRE!$C$5="6ª FAIXA",DRE!$C$4,0),0) -> 0 | G7: =(F7*D7-E7)/F7 -> #DIV/0! | I7: 0.135 | J7: 0.1 | K7: 0.421 | L7: 0.2827 | M7: 0.0613 | N7: 0 | O7: 0 | P7: 0 | Q7: =SUM(I7:P7) -> 1 | S7: =N7+O7 -> 0 | T7: =S7*G7 -> #DIV/0! | U7: =L7+M7 -> 0.344 | V7: =U7*G7 -> #DIV/0! | W7: =Q7-S7-U7 -> 0.656 | X7: =W7*G7 -> #DIV/0!
A9: ANEXO II | B9: MÍNIMO | C9: MÁXIMO | D9: FAIXA | E9: DEDUZIR | I9: IRPJ | J9: CSLL | K9: CPP | L9: COFINS | M9: PIS | N9: ICMS | O9: ISS | P9: IPI | Q9: TOTAL
A10: 1ª FAIXA | B10: 0 | C10: 180000 | D10: 0.045 | E10: 0 | F10: =IF(DRE!$C$3="ANEXO II - INDÚSTRIA",IF(DRE!$C$5="1ª FAIXA",DRE!$C$4,0),0) -> 0 | G10: =(F10*D10-E10)/F10 -> #DIV/0! | I10: 0.055 | J10: 0.035 | K10: 0.375 | L10: 0.1151 | M10: 0.0249 | N10: 0.32 | O10: 0 | P10: 0.075 | Q10: =SUM(I10:P10) -> 1 | S10: =N10+O10 -> 0.32 | T10: =S10*G10 -> #DIV/0! | U10: =L10+M10 -> 0.14 | V10: =U10*G10 -> #DIV/0! | W10: =Q10-S10-U10 -> 0.54 | X10: =W10*G10 -> #DIV/0!
A11: 2ª FAIXA | B11: =C10+0.01 -> 180000.01 | C11: =C10*2 -> 360000 | D11: 0.078 | E11: 5940 | F11: =IF(DRE!$C$3="ANEXO II - INDÚSTRIA",IF(DRE!$C$5="2ª FAIXA",DRE!$C$4,0),0) -> 0 | G11: =(F11*D11-E11)/F11 -> #DIV/0! | I11: 0.055 | J11: 0.035 | K11: 0.375 | L11: 0.1151 | M11: 0.0249 | N11: 0.32 | O11: 0 | P11: 0.075 | Q11: =SUM(I11:P11) -> 1 | S11: =N11+O11 -> 0.32 | T11: =S11*G11 -> #DIV/0! | U11: =L11+M11 -> 0.14 | V11: =U11*G11 -> #DIV/0! | W11: =Q11-S11-U11 -> 0.54 | X11: =W11*G11 -> #DIV/0!
A12: 3ª FAIXA | B12: =C11+0.01 -> 360000.01 | C12: =C11*2 -> 720000 | D12: 0.1 | E12: 13860 | F12: =IF(DRE!$C$3="ANEXO II - INDÚSTRIA",IF(DRE!$C$5="3ª FAIXA",DRE!$C$4,0),0) -> 0 | G12: =(F12*D12-E12)/F12 -> #DIV/0! | I12: 0.055 | J12: 0.035 | K12: 0.375 | L12: 0.1151 | M12: 0.0249 | N12: 0.32 | O12: 0 | P12: 0.075 | Q12: =SUM(I12:P12) -> 1 | S12: =N12+O12 -> 0.32 | T12: =S12*G12 -> #DIV/0! | U12: =L12+M12 -> 0.14 | V12: =U12*G12 -> #DIV/0! | W12: =Q12-S12-U12 -> 0.54 | X12: =W12*G12 -> #DIV/0!
A13: 4ª FAIXA | B13: =C12+0.01 -> 720000.01 | C13: 1800000 | D13: 0.112 | E13: 22500 | F13: =IF(DRE!$C$3="ANEXO II - INDÚSTRIA",IF(DRE!$C$5="4ª FAIXA",DRE!$C$4,0),0) -> 0 | G13: =(F13*D13-E13)/F13 -> #DIV/0! | I13: 0.055 | J13: 0.035 | K13: 0.375 | L13: 0.1151 | M13: 0.0249 | N13: 0.32 | O13: 0 | P13: 0.075 | Q13: =SUM(I13:P13) -> 1 | S13: =N13+O13 -> 0.32 | T13: =S13*G13 -> #DIV/0! | U13: =L13+M13 -> 0.14 | V13: =U13*G13 -> #DIV/0! | W13: =Q13-S13-U13 -> 0.54 | X13: =W13*G13 -> #DIV/0!
A14: 5ª FAIXA | B14: =C13+0.01 -> 1800000 | C14: =C13*2 -> 3600000 | D14: 0.147 | E14: 85500 | F14: =IF(DRE!$C$3="ANEXO II - INDÚSTRIA",IF(DRE!$C$5="5ª FAIXA",DRE!$C$4,0),0) -> 0 | G14: =(F14*D14-E14)/F14 -> #DIV/0! | I14: 0.055 | J14: 0.035 | K14: 0.375 | L14: 0.1151 | M14: 0.0249 | N14: 0.32 | O14: 0 | P14: 0.075 | Q14: =SUM(I14:P14) -> 1 | S14: =N14+O14 -> 0.32 | T14: =S14*G14 -> #DIV/0! | U14: =L14+M14 -> 0.14 | V14: =U14*G14 -> #DIV/0! | W14: =Q14-S14-U14 -> 0.54 | X14: =W14*G14 -> #DIV/0!
A15: 6ª FAIXA | B15: =C14+0.01 -> 3600000 | C15: 4800000 | D15: 0.3 | E15: 720000 | F15: =IF(DRE!$C$3="ANEXO II - INDÚSTRIA",IF(DRE!$C$5="6ª FAIXA",DRE!$C$4,0),0) -> 0 | G15: =(F15*D15-E15)/F15 -> #DIV/0! | I15: 0.085 | J15: 0.075 | K15: 0.235 | L15: 0.2096 | M15: 0.0454 | N15: 0 | O15: 0 | P15: 0.35 | Q15: =SUM(I15:P15) -> 1 | S15: =N15+O15 -> 0 | T15: =S15*G15 -> #DIV/0! | U15: =L15+M15 -> 0.255 | V15: =U15*G15 -> #DIV/0! | W15: =Q15-S15-U15 -> 0.745 | X15: =W15*G15 -> #DIV/0!
A17: ANEXO III | B17: MÍNIMO | C17: MÁXIMO | D17: FAIXA | E17: DEDUZIR | I17: IRPJ | J17: CSLL | K17: CPP | L17: COFINS | M17: PIS | N17: ICMS | O17: ISS | P17: IPI | Q17: TOTAL
A18: 1ª FAIXA | B18: 0 | C18: 180000 | D18: 0.06 | E18: 0 | F18: =IF(DRE!$C$3="ANEXO III - SERVIÇOS",IF(DRE!$C$5="1ª FAIXA",DRE!$C$4,0),0) -> 0 | G18: =(F18*D18-E18)/F18 -> #DIV/0! | I18: 0.04 | J18: 0.035 | K18: 0.434 | L18: 0.1282 | M18: 0.0278 | N18: 0 | O18: 0.335 | P18: 0 | Q18: =SUM(I18:P18) -> 1 | S18: =N18+O18 -> 0.335 | T18: =S18*G18 -> #DIV/0! | U18: =L18+M18 -> 0.156 | V18: =U18*G18 -> #DIV/0! | W18: =Q18-S18-U18 -> 0.509 | X18: =W18*G18 -> #DIV/0!
A19: 2ª FAIXA | B19: =C18+0.01 -> 180000.01 | C19: =C18*2 -> 360000 | D19: 0.112 | E19: 9360 | F19: =IF(DRE!$C$3="ANEXO III - SERVIÇOS",IF(DRE!$C$5="2ª FAIXA",DRE!$C$4,0),0) -> 0 | G19: =(F19*D19-E19)/F19 -> #DIV/0! | I19: 0.04 | J19: 0.035 | K19: 0.434 | L19: 0.1405 | M19: 0.0305 | N19: 0 | O19: 0.32 | P19: 0 | Q19: =SUM(I19:P19) -> 1 | S19: =N19+O19 -> 0.32 | T19: =S19*G19 -> #DIV/0! | U19: =L19+M19 -> 0.171 | V19: =U19*G19 -> #DIV/0! | W19: =Q19-S19-U19 -> 0.509 | X19: =W19*G19 -> #DIV/0!
A20: 3ª FAIXA | B20: =C19+0.01 -> 360000.01 | C20: =C19*2 -> 720000 | D20: 0.135 | E20: 17640 | F20: =IF(DRE!$C$3="ANEXO III - SERVIÇOS",IF(DRE!$C$5="3ª FAIXA",DRE!$C$4,0),0) -> 0 | G20: =(F20*D20-E20)/F20 -> #DIV/0! | I20: 0.04 | J20: 0.035 | K20: 0.434 | L20: 0.1364 | M20: 0.0296 | N20: 0 | O20: 0.325 | P20: 0 | Q20: =SUM(I20:P20) -> 1 | S20: =N20+O20 -> 0.325 | T20: =S20*G20 -> #DIV/0! | U20: =L20+M20 -> 0.166 | V20: =U20*G20 -> #DIV/0! | W20: =Q20-S20-U20 -> 0.509 | X20: =W20*G20 -> #DIV/0!
A21: 4ª FAIXA | B21: =C20+0.01 -> 720000.01 | C21: 1800000 | D21: 0.16 | E21: 35640 | F21: =IF(DRE!$C$3="ANEXO III - SERVIÇOS",IF(DRE!$C$5="4ª FAIXA",DRE!$C$4,0),0) -> 0 | G21: =(F21*D21-E21)/F21 -> #DIV/0! | I21: 0.04 | J21: 0.035 | K21: 0.434 | L21: 0.1364 | M21: 0.0296 | N21: 0 | O21: 0.325 | P21: 0 | Q21: =SUM(I21:P21) -> 1 | S21: =N21+O21 -> 0.325 | T21: =S21*G21 -> #DIV/0! | U21: =L21+M21 -> 0.166 | V21: =U21*G21 -> #DIV/0! | W21: =Q21-S21-U21 -> 0.509 | X21: =W21*G21 -> #DIV/0!
A22: 5ª FAIXA | B22: =C21+0.01 -> 1800000 | C22: =C21*2 -> 3600000 | D22: 0.21 | E22: 125640 | F22: =IF(DRE!$C$3="ANEXO III - SERVIÇOS",IF(DRE!$C$5="5ª FAIXA",DRE!$C$4,0),0) -> 0 | G22: =(F22*D22-E22)/F22 -> #DIV/0! | I22: 0.04 | J22: 0.035 | K22: 0.434 | L22: 0.1282 | M22: 0.0278 | N22: 0 | O22: 0.335 | P22: 0 | Q22: =SUM(I22:P22) -> 1 | S22: =N22+O22 -> 0.335 | T22: =S22*G22 -> #DIV/0! | U22: =L22+M22 -> 0.156 | V22: =U22*G22 -> #DIV/0! | W22: =Q22-S22-U22 -> 0.509 | X22: =W22*G22 -> #DIV/0!
A23: 6ª FAIXA | B23: =C22+0.01 -> 3600000 | C23: 4800000 | D23: 0.33 | E23: 648000 | F23: =IF(DRE!$C$3="ANEXO III - SERVIÇOS",IF(DRE!$C$5="6ª FAIXA",DRE!$C$4,0),0) -> 0 | G23: =(F23*D23-E23)/F23 -> #DIV/0! | I23: 0.35 | J23: 0.15 | K23: 0.305 | L23: 0.1603 | M23: 0.0347 | N23: 0 | O23: 0 | P23: 0 | Q23: =SUM(I23:P23) -> 1 | S23: =N23+O23 -> 0 | T23: =S23*G23 -> #DIV/0! | U23: =L23+M23 -> 0.195 | V23: =U23*G23 -> #DIV/0! | W23: =Q23-S23-U23 -> 0.805 | X23: =W23*G23 -> #DIV/0!
A25: ANEXO IV | B25: MÍNIMO | C25: MÁXIMO | D25: FAIXA | E25: DEDUZIR | I25: IRPJ | J25: CSLL | K25: CPP | L25: COFINS | M25: PIS | N25: ICMS | O25: ISS | P25: IPI | Q25: TOTAL
A26: 1ª FAIXA | B26: 0 | C26: 180000 | D26: 0.045 | E26: 0 | F26: =IF(DRE!$C$3="ANEXO IV - SERVIÇOS",IF(DRE!$C$5="1ª FAIXA",DRE!$C$4,0),0) -> 0 | G26: =(F26*D26-E26)/F26 -> #DIV/0! | I26: 0.188 | J26: 0.152 | K26: 0 | L26: 0.1767 | M26: 0.0383 | N26: 0 | O26: 0.445 | P26: 0 | Q26: =SUM(I26:P26) -> 1 | S26: =N26+O26 -> 0.445 | T26: =S26*G26 -> #DIV/0! | U26: =L26+M26 -> 0.215 | V26: =U26*G26 -> #DIV/0! | W26: =Q26-S26-U26 -> 0.34 | X26: =W26*G26 -> #DIV/0!
A27: 2ª FAIXA | B27: =C26+0.01 -> 180000.01 | C27: =C26*2 -> 360000 | D27: 0.09 | E27: 8100 | F27: =IF(DRE!$C$3="ANEXO IV - SERVIÇOS",IF(DRE!$C$5="2ª FAIXA",DRE!$C$4,0),0) -> 0 | G27: =(F27*D27-E27)/F27 -> #DIV/0! | I27: 0.198 | J27: 0.152 | K27: 0 | L27: 0.2055 | M27: 0.0445 | N27: 0 | O27: 0.4 | P27: 0 | Q27: =SUM(I27:P27) -> 1 | S27: =N27+O27 -> 0.4 | T27: =S27*G27 -> #DIV/0! | U27: =L27+M27 -> 0.25 | V27: =U27*G27 -> #DIV/0! | W27: =Q27-S27-U27 -> 0.35 | X27: =W27*G27 -> #DIV/0!
A28: 3ª FAIXA | B28: =C27+0.01 -> 360000.01 | C28: =C27*2 -> 720000 | D28: 0.102 | E28: 12420 | F28: =IF(DRE!$C$3="ANEXO IV - SERVIÇOS",IF(DRE!$C$5="3ª FAIXA",DRE!$C$4,0),0) -> 0 | G28: =(F28*D28-E28)/F28 -> #DIV/0! | I28: 0.208 | J28: 0.152 | K28: 0 | L28: 0.1973 | M28: 0.0427 | N28: 0 | O28: 0.4 | P28: 0 | Q28: =SUM(I28:P28) -> 1 | S28: =N28+O28 -> 0.4 | T28: =S28*G28 -> #DIV/0! | U28: =L28+M28 -> 0.24 | V28: =U28*G28 -> #DIV/0! | W28: =Q28-S28-U28 -> 0.36 | X28: =W28*G28 -> #DIV/0!
A29: 4ª FAIXA | B29: =C28+0.01 -> 720000.01 | C29: 1800000 | D29: 0.14 | E29: 39780 | F29: =IF(DRE!$C$3="ANEXO IV - SERVIÇOS",IF(DRE!$C$5="4ª FAIXA",DRE!$C$4,0),0) -> 0 | G29: =(F29*D29-E29)/F29 -> #DIV/0! | I29: 0.178 | J29: 0.192 | K29: 0 | L29: 0.189 | M29: 0.041 | N29: 0 | O29: 0.4 | P29: 0 | Q29: =SUM(I29:P29) -> 1 | S29: =N29+O29 -> 0.4 | T29: =S29*G29 -> #DIV/0! | U29: =L29+M29 -> 0.23 | V29: =U29*G29 -> #DIV/0! | W29: =Q29-S29-U29 -> 0.37 | X29: =W29*G29 -> #DIV/0!
A30: 5ª FAIXA | B30: =C29+0.01 -> 1800000 | C30: =C29*2 -> 3600000 | D30: 0.22 | E30: 183780 | F30: =IF(DRE!$C$3="ANEXO IV - SERVIÇOS",IF(DRE!$C$5="5ª FAIXA",DRE!$C$4,0),0) -> 0 | G30: =(F30*D30-E30)/F30 -> #DIV/0! | I30: 0.188 | J30: 0.192 | K30: 0 | L30: 0.1808 | M30: 0.0392 | N30: 0 | O30: 0.4 | P30: 0 | Q30: =SUM(I30:P30) -> 1 | S30: =N30+O30 -> 0.4 | T30: =S30*G30 -> #DIV/0! | U30: =L30+M30 -> 0.22 | V30: =U30*G30 -> #DIV/0! | W30: =Q30-S30-U30 -> 0.38 | X30: =W30*G30 -> #DIV/0!
A31: 6ª FAIXA | B31: =C30+0.01 -> 3600000 | C31: 4800000 | D31: 0.33 | E31: 828000 | F31: =IF(DRE!$C$3="ANEXO IV - SERVIÇOS",IF(DRE!$C$5="6ª FAIXA",DRE!$C$4,0),0) -> 0 | G31: =(F31*D31-E31)/F31 -> #DIV/0! | I31: 0.535 | J31: 0.215 | K31: 0 | L31: 0.2055 | M31: 0.0445 | N31: 0 | O31: 0 | P31: 0 | Q31: =SUM(I31:P31) -> 1 | S31: =N31+O31 -> 0 | T31: =S31*G31 -> #DIV/0! | U31: =L31+M31 -> 0.25 | V31: =U31*G31 -> #DIV/0! | W31: =Q31-S31-U31 -> 0.75 | X31: =W31*G31 -> #DIV/0!
A33: ANEXO V | B33: MÍNIMO | C33: MÁXIMO | D33: FAIXA | E33: DEDUZIR | I33: IRPJ | J33: CSLL | K33: CPP | L33: COFINS | M33: PIS | N33: ICMS | O33: ISS | P33: IPI | Q33: TOTAL
A34: 1ª FAIXA | B34: 0 | C34: 180000 | D34: 0.155 | E34: 0 | F34: =IF(DRE!$C$3="ANEXO V - SERVIÇOS",IF(DRE!$C$5="1ª FAIXA",DRE!$C$4,0),0) -> 0 | G34: =(F34*D34-E34)/F34 -> #DIV/0! | I34: 0.25 | J34: 0.15 | K34: 0.2885 | L34: 0.141 | M34: 0.0305 | N34: 0 | O34: 0.14 | P34: 0 | Q34: =SUM(I34:P34) -> 1 | S34: =N34+O34 -> 0.14 | T34: =S34*G34 -> #DIV/0! | U34: =L34+M34 -> 0.1715 | V34: =U34*G34 -> #DIV/0! | W34: =Q34-S34-U34 -> 0.6885 | X34: =W34*G34 -> #DIV/0!
A35: 2ª FAIXA | B35: =C34+0.01 -> 180000.01 | C35: =C34*2 -> 360000 | D35: 0.18 | E35: 4500 | F35: =IF(DRE!$C$3="ANEXO V - SERVIÇOS",IF(DRE!$C$5="2ª FAIXA",DRE!$C$4,0),0) -> 0 | G35: =(F35*D35-E35)/F35 -> #DIV/0! | I35: 0.23 | J35: 0.15 | K35: 0.2785 | L35: 0.141 | M35: 0.0305 | N35: 0 | O35: 0.17 | P35: 0 | Q35: =SUM(I35:P35) -> 1 | S35: =N35+O35 -> 0.17 | T35: =S35*G35 -> #DIV/0! | U35: =L35+M35 -> 0.1715 | V35: =U35*G35 -> #DIV/0! | W35: =Q35-S35-U35 -> 0.6585 | X35: =W35*G35 -> #DIV/0!
A36: 3ª FAIXA | B36: =C35+0.01 -> 360000.01 | C36: =C35*2 -> 720000 | D36: 0.195 | E36: 9900 | F36: =IF(DRE!$C$3="ANEXO V - SERVIÇOS",IF(DRE!$C$5="3ª FAIXA",DRE!$C$4,0),0) -> 0 | G36: =(F36*D36-E36)/F36 -> #DIV/0! | I36: 0.24 | J36: 0.15 | K36: 0.2385 | L36: 0.1492 | M36: 0.0323 | N36: 0 | O36: 0.19 | P36: 0 | Q36: =SUM(I36:P36) -> 1 | S36: =N36+O36 -> 0.19 | T36: =S36*G36 -> #DIV/0! | U36: =L36+M36 -> 0.1815 | V36: =U36*G36 -> #DIV/0! | W36: =Q36-S36-U36 -> 0.6285 | X36: =W36*G36 -> #DIV/0!
A37: 4ª FAIXA | B37: =C36+0.01 -> 720000.01 | C37: 1800000 | D37: 0.205 | E37: 17100 | F37: =IF(DRE!$C$3="ANEXO V - SERVIÇOS",IF(DRE!$C$5="4ª FAIXA",DRE!$C$4,0),0) -> 0 | G37: =(F37*D37-E37)/F37 -> #DIV/0! | I37: 0.21 | J37: 0.15 | K37: 0.2385 | L37: 0.1574 | M37: 0.0341 | N37: 0 | O37: 0.21 | P37: 0 | Q37: =SUM(I37:P37) -> 1 | S37: =N37+O37 -> 0.21 | T37: =S37*G37 -> #DIV/0! | U37: =L37+M37 -> 0.1915 | V37: =U37*G37 -> #DIV/0! | W37: =Q37-S37-U37 -> 0.5985 | X37: =W37*G37 -> #DIV/0!
A38: 5ª FAIXA | B38: =C37+0.01 -> 1800000 | C38: =C37*2 -> 3600000 | D38: 0.23 | E38: 62100 | F38: =IF(DRE!$C$3="ANEXO V - SERVIÇOS",IF(DRE!$C$5="5ª FAIXA",DRE!$C$4,0),0) -> 0 | G38: =(F38*D38-E38)/F38 -> #DIV/0! | I38: 0.23 | J38: 0.125 | K38: 0.2385 | L38: 0.141 | M38: 0.0305 | N38: 0 | O38: 0.235 | P38: 0 | Q38: =SUM(I38:P38) -> 1 | S38: =N38+O38 -> 0.235 | T38: =S38*G38 -> #DIV/0! | U38: =L38+M38 -> 0.1715 | V38: =U38*G38 -> #DIV/0! | W38: =Q38-S38-U38 -> 0.5935 | X38: =W38*G38 -> #DIV/0!
A39: 6ª FAIXA | B39: =C38+0.01 -> 3600000 | C39: 4800000 | D39: 0.305 | E39: 540000 | F39: =IF(DRE!$C$3="ANEXO V - SERVIÇOS",IF(DRE!$C$5="6ª FAIXA",DRE!$C$4,0),0) -> 0 | G39: =(F39*D39-E39)/F39 -> #DIV/0! | I39: 0.35 | J39: 0.155 | K39: 0.295 | L39: 0.1644 | M39: 0.0356 | N39: 0 | O39: 0 | P39: 0 | Q39: =SUM(I39:P39) -> 1 | S39: =N39+O39 -> 0 | T39: =S39*G39 -> #DIV/0! | U39: =L39+M39 -> 0.2 | V39: =U39*G39 -> #DIV/0! | W39: =Q39-S39-U39 -> 0.8 | X39: =W39*G39 -> #DIV/0!
